mainchecker/__init__.py
mainchecker-1.0.1.dist-info/DESCRIPTION.rst
mainchecker-1.0.1.dist-info/METADATA
mainchecker-1.0.1.dist-info/RECORD
mainchecker-1.0.1.dist-info/WHEEL
mainchecker-1.0.1.dist-info/metadata.json
mainchecker-1.0.1.dist-info/top_level.txt
mainchecker-1.0.1.dist-info/zip-safe
