Metadata-Version: 2.0
Name: mainchecker
Version: 1.0.1
Summary: Easy way to implement the 'if __name__ == '__main__' '
Home-page: UNKNOWN
Author: PokestarFan
Author-email: pokestarfan@yahoo.com
License: MIT
Platform: UNKNOWN
